LICENSE
README.md
setup.py
lib_analytics_cofco/__init__.py
lib_analytics_cofco/wrapper.py
wrapper_analytics.egg-info/PKG-INFO
wrapper_analytics.egg-info/SOURCES.txt
wrapper_analytics.egg-info/dependency_links.txt
wrapper_analytics.egg-info/top_level.txt