Metadata-Version: 2.1
Name: wrapper-analytics
Version: 0.0.1
Summary: Teste
Author: Lucas Martim
Author-email: 
License-File: LICENSE
